CONTRIBUTING.md
LICENSE
typeline/__init__.py
typeline/_data_types.py
typeline/_reader.py
typeline/_writer.py
typeline/py.typed
typeline-0.7.0.dist-info/LICENSE
typeline-0.7.0.dist-info/METADATA
typeline-0.7.0.dist-info/WHEEL
typeline-0.7.0.dist-info/RECORD
