Metadata-Version: 2.1
Name: typeline
Version: 0.7.0
Summary: Write dataclasses to delimited text formats and read them back again.
Home-page: https://github.com/clintval/typeline
License: MIT
Keywords: dataclass,msgspec,IO,delimited,CSV,TSV
Author: Clint Valentine
Author-email: valentine.clint@gmail.com
Requires-Python: >=3.10.0,<4.0.0
Classifier: Development Status :: 3 - Alpha
Classifier: Environment :: Console
Classifier: Intended Audience :: Developers
Classifier: Intended Audience :: Science/Research
Classifier: License :: OSI Approved :: MIT License
Classifier: Natural Language :: English
Classifier: Operating System :: OS Independent
Classifier: Programming Language :: Python :: 3
Classifier: Programming Language :: Python :: 3.10
Classifier: Programming Language :: Python :: 3.11
Classifier: Programming Language :: Python :: 3.12
Classifier: Programming Language :: Python :: 3.13
Classifier: Topic :: File Formats
Classifier: Topic :: Software Development :: Documentation
Classifier: Topic :: Software Development :: Libraries :: Python Modules
Classifier: Typing :: Typed
Requires-Dist: msgspec (>=0.18,<0.19)
Requires-Dist: typing-extensions (>=4.12,<5.0)
Project-URL: Repository, https://github.com/clintval/typeline
